printer/__init__.py
printer/font_helper.py
printer/http.py
printer/painter.py
printer/run.py
printer/utils.py
printer/version.py
TerminalPrinter-2.3.2.dist-info/LICENSE
TerminalPrinter-2.3.2.dist-info/METADATA
TerminalPrinter-2.3.2.dist-info/WHEEL
TerminalPrinter-2.3.2.dist-info/entry_points.txt
TerminalPrinter-2.3.2.dist-info/top_level.txt
TerminalPrinter-2.3.2.dist-info/RECORD
