Metadata-Version: 2.1
Name: TerminalPrinter
Version: 2.3.2
Summary: 终端图片、文字生成器
Home-page: https://github.com/hellflame/terminal_printer
Author: hellflame
Author-email: hellflamedly@gmail.com
License: MIT
Keywords: 字符画,终端打印
Classifier: Development Status :: 5 - Production/Stable
Classifier: Intended Audience :: Developers
Classifier: Programming Language :: Python :: 2.7
Classifier: Programming Language :: Python :: 3.6
Classifier: Programming Language :: Python :: 3.10
Classifier: Environment :: Console
Classifier: License :: OSI Approved :: MIT License
Classifier: Operating System :: MacOS
Classifier: Operating System :: MacOS :: MacOS X
Classifier: Operating System :: POSIX
Classifier: Operating System :: POSIX :: Linux
Classifier: Topic :: Text Processing :: General
Classifier: Topic :: Terminals
Classifier: Topic :: Games/Entertainment
License-File: LICENSE
Requires-Dist: Pillow
